mcp_weather_sse_dashi/__init__.py
mcp_weather_sse_dashi/__main__.py
mcp_weather_sse_dashi/server.py
mcp_weather_sse_dashi-0.1.0.dist-info/METADATA
mcp_weather_sse_dashi-0.1.0.dist-info/WHEEL
mcp_weather_sse_dashi-0.1.0.dist-info/entry_points.txt
mcp_weather_sse_dashi-0.1.0.dist-info/top_level.txt
mcp_weather_sse_dashi-0.1.0.dist-info/RECORD
